<?xml version="1.0" encoding="UTF-8"?><record_update sys_domain="global" table="sys_ux_page_property">
    <sys_ux_page_property action="DELETE">
        <choices/>
        <description/>
        <name>chrome_footer</name>
        <page display_value="Domain Management">114051a2eb610a9031c8f17fcad0cd6f</page>
        <required_translations>[ ]</required_translations>
        <route/>
        <suffix/>
        <sys_class_name>sys_ux_page_property</sys_class_name>
        <sys_created_by>clone.user</sys_created_by>
        <sys_created_on>2024-04-16 18:17:33</sys_created_on>
        <sys_domain>global</sys_domain>
        <sys_domain_path>/</sys_domain_path>
        <sys_id>f7409d22eb610a9031c8f17fcad0cd47</sys_id>
        <sys_mod_count>0</sys_mod_count>
        <sys_name>chrome_footer</sys_name>
        <sys_package display_value="Domain Management" source="x_snc_domain_man_0">500e9fe387fa311041c11f483cbb351d</sys_package>
        <sys_policy/>
        <sys_scope display_value="Domain Management">500e9fe387fa311041c11f483cbb351d</sys_scope>
        <sys_update_name>sys_ux_page_property_f7409d22eb610a9031c8f17fcad0cd47</sys_update_name>
        <sys_updated_by>clone.user</sys_updated_by>
        <sys_updated_on>2024-04-16 18:17:33</sys_updated_on>
        <type>json</type>
        <unique_name>x_snc_domain_man_0.114051a2eb610a9031c8f17fcad0cd6f.root.chrome_footer</unique_name>
        <value>{"public_page":{"enable_footer_topbar":false,"footer_topbar_options":{},"enable_footer_bar":false,"footer_bar_options":{}}}</value>
    </sys_ux_page_property>
    <sys_translated_text action="DELETE" query="documentkey=f7409d22eb610a9031c8f17fcad0cd47"/>
<sys_update_version action="INSERT_OR_UPDATE">
        <action>DELETE</action>
        <application display_value="Domain Management">500e9fe387fa311041c11f483cbb351d</application>
        <file_path/>
        <instance_id>25b0627bdb66e8900ae3ac44d4961997</instance_id>
        <instance_name>tblevinse2eitomdsdemo</instance_name>
        <name>sys_ux_page_property_f7409d22eb610a9031c8f17fcad0cd47</name>
        <payload><![CDATA[<?xml version="1.0" encoding="UTF-8"?><record_update sys_domain="global" table="sys_ux_page_property">
    <sys_ux_page_property action="INSERT_OR_UPDATE">
        <choices/>
        <description/>
        <name>chrome_footer</name>
        <page display_value="Domain Management">114051a2eb610a9031c8f17fcad0cd6f</page>
        <required_translations>[ ]</required_translations>
        <route/>
        <suffix/>
        <sys_class_name>sys_ux_page_property</sys_class_name>
        <sys_created_by>clone.user</sys_created_by>
        <sys_created_on>2024-04-16 18:17:33</sys_created_on>
        <sys_domain>global</sys_domain>
        <sys_domain_path>/</sys_domain_path>
        <sys_id>f7409d22eb610a9031c8f17fcad0cd47</sys_id>
        <sys_mod_count>0</sys_mod_count>
        <sys_name>chrome_footer</sys_name>
        <sys_package display_value="Domain Management" source="x_snc_domain_man_0">500e9fe387fa311041c11f483cbb351d</sys_package>
        <sys_policy/>
        <sys_scope display_value="Domain Management">500e9fe387fa311041c11f483cbb351d</sys_scope>
        <sys_update_name>sys_ux_page_property_f7409d22eb610a9031c8f17fcad0cd47</sys_update_name>
        <sys_updated_by>clone.user</sys_updated_by>
        <sys_updated_on>2024-04-16 18:17:33</sys_updated_on>
        <type>json</type>
        <unique_name>x_snc_domain_man_0.114051a2eb610a9031c8f17fcad0cd6f.root.chrome_footer</unique_name>
        <value>{"public_page":{"enable_footer_topbar":false,"footer_topbar_options":{},"enable_footer_bar":false,"footer_bar_options":{}}}</value>
    </sys_ux_page_property>
    <sys_translated_text action="delete_multiple" query="documentkey=f7409d22eb610a9031c8f17fcad0cd47"/>
</record_update>]]></payload>
        <payload_hash>-983733768</payload_hash>
        <record_name>chrome_footer</record_name>
        <reverted_from/>
        <source>58e073d787e9c690a3a80f68cebb3538</source>
        <source_table>sys_upgrade_history</source_table>
        <state>previous</state>
        <sys_created_by>admin</sys_created_by>
        <sys_created_on>2024-04-19 13:57:13</sys_created_on>
        <sys_id>b371bbdb87e9c690a3a80f68cebb35fc</sys_id>
        <sys_mod_count>0</sys_mod_count>
        <sys_recorded_at>18ef6a5a24d0000001</sys_recorded_at>
        <sys_updated_by>admin</sys_updated_by>
        <sys_updated_on>2024-04-19 13:57:13</sys_updated_on>
        <type>UX Page Property</type>
        <update_guid>7f71bbdbfce9c6900876609772dfb6fb</update_guid>
        <update_guid_history>7f71bbdbfce9c6900876609772dfb6fb:0,e3fd6f9b38a9c690f9923d10aa5cf859:1187072924,31262f17e769c69064194ea5c3e2e8f7:-983733768</update_guid_history>
    </sys_update_version>
    <sys_metadata_delete action="INSERT_OR_UPDATE">
        <sys_audit_delete/>
        <sys_class_name>sys_metadata_delete</sys_class_name>
        <sys_created_by>clone.user</sys_created_by>
        <sys_created_on>2024-05-03 10:31:09</sys_created_on>
        <sys_db_object display_value="" name="sys_ux_page_property">sys_ux_page_property</sys_db_object>
        <sys_id>1876f1f4f8d84e928dd6db2f361c4424</sys_id>
        <sys_metadata>f7409d22eb610a9031c8f17fcad0cd47</sys_metadata>
        <sys_mod_count>0</sys_mod_count>
        <sys_name>chrome_footer</sys_name>
        <sys_package display_value="Domain Management" source="x_snc_domain_man_0">500e9fe387fa311041c11f483cbb351d</sys_package>
        <sys_parent/>
        <sys_policy/>
        <sys_scope display_value="Domain Management">500e9fe387fa311041c11f483cbb351d</sys_scope>
        <sys_scope_delete display_value="">75d987b2b4634c4d9b2b4760c2f00641</sys_scope_delete>
        <sys_update_name>sys_ux_page_property_f7409d22eb610a9031c8f17fcad0cd47</sys_update_name>
        <sys_update_version display_value="sys_ux_page_property_f7409d22eb610a9031c8f17fcad0cd47">b371bbdb87e9c690a3a80f68cebb35fc</sys_update_version>
        <sys_updated_by>clone.user</sys_updated_by>
        <sys_updated_on>2024-05-03 10:31:09</sys_updated_on>
        <u_number/>
    </sys_metadata_delete>
</record_update>
